unscrapulous/__init__.py
unscrapulous/arbitration_awards_bse.py
unscrapulous/arbitration_awards_nse.py
unscrapulous/bse_defaulter_and_expelled_members.py
unscrapulous/config.toml
unscrapulous/icex_defaulter_members.py
unscrapulous/icex_expelled_members.py
unscrapulous/income_tax_defaulters.py
unscrapulous/irda_blacklisted.py
unscrapulous/mca_company_defaulter_list.py
unscrapulous/mca_director_defaulter_list.py
unscrapulous/mca_director_disqualified_list.py
unscrapulous/mca_proclaimed_offenders_ind.py
unscrapulous/mcx_action_ap.py
unscrapulous/mcx_defaulter_members.py
unscrapulous/mcx_secretaries_defaulter_list.py
unscrapulous/mse_arbitral_awards.py
unscrapulous/ncdex_suspended_defaulted_expelled_debarred_members.py
unscrapulous/nse_defaulted_members.py
unscrapulous/nse_expelled_members.py
unscrapulous/nse_regulatory_defaulting_clients.py
unscrapulous/sebi_debarred_bse.py
unscrapulous/sebi_debarred_nse.py
unscrapulous/sfio_convicted.py
unscrapulous/sfio_proclaimed_offenders.py
unscrapulous/unsc_1988.py
unscrapulous/unsc_consolidated_list.py
unscrapulous/unscrapulous.py
unscrapulous/utils.py
unscrapulous/wildlife_crime_convicts.py
unscrapulous-0.1.4.dist-info/entry_points.txt
unscrapulous-0.1.4.dist-info/LICENSE
unscrapulous-0.1.4.dist-info/WHEEL
unscrapulous-0.1.4.dist-info/METADATA
unscrapulous-0.1.4.dist-info/RECORD
